securenotes_client/__init__.py
securenotes_client/securenotes.py
securenotes_client/securenotes_api.py
securenotes_client-0.2.1.data/scripts/securenotes.py
securenotes_client-0.2.1.dist-info/LICENSE
securenotes_client-0.2.1.dist-info/METADATA
securenotes_client-0.2.1.dist-info/WHEEL
securenotes_client-0.2.1.dist-info/top_level.txt
securenotes_client-0.2.1.dist-info/RECORD
