Metadata-Version: 2.1
Name: securenotes-client
Version: 0.2.1
Summary: Command line client for SecureNotes
Home-page: https://github.com/crazyscientist/secure-notes-client
Author: Andreas Hasenkopf
Author-email: andreas@hasenkopf.xyz
License: UNKNOWN
Project-URL: Bug Tracker, https://github.com/crazyscientist/secure-notes-client/issues
Project-URL: Documentation, https://readthedocs.org/projects/secure-notes-client/
Project-URL: Source Code, https://github.com/crazyscientist/secure-notes-client
Platform: UNKNOWN
Classifier: Development Status :: 3 - Alpha
Classifier: Environment :: Console
Classifier: Programming Language :: Python :: 3
Classifier: Programming Language :: Python :: 3.5
Classifier: Programming Language :: Python :: 3.6
Classifier: Programming Language :: Python :: 3.7
Classifier: License :: OSI Approved :: MIT License
Classifier: Operating System :: OS Independent
Requires-Python: >=3.5
Requires-Dist: requests
Requires-Dist: pycryptodomex
Requires-Dist: mdv
